README.md
setup.py
periodrangepy/__init__.py
periodrangepy/periodrange.py
periodrangepy.egg-info/PKG-INFO
periodrangepy.egg-info/SOURCES.txt
periodrangepy.egg-info/dependency_links.txt
periodrangepy.egg-info/requires.txt
periodrangepy.egg-info/top_level.txt