Metadata-Version: 2.1
Name: periodrangepy
Version: 2020.6.18
Summary: Генерация списка периодов
Home-page: https://github.com/pavelmaksimov/periodrangepy
Author: Pavel Maksimov
License: MIT
Keywords: date,period,python,range
Platform: UNKNOWN
Classifier: Programming Language :: Python :: 3
Classifier: License :: OSI Approved :: MIT License
Requires-Python: >=3.5
